gilly_utilities/__init__.py
gilly_utilities/datetime64.py
gilly_utilities/extras.py
gilly_utilities/geospatial.py
gilly_utilities/manipulation.py
gilly_utilities/math.py
gilly_utilities/meteorology.py
gilly_utilities/nanfunctions.py
gilly_utilities/plotting.py
gilly_utilities/setup.py
gilly_utilities/stats.py
gilly_utilities/system.py
gilly_utilities-0.9.6.dist-info/LICENSE
gilly_utilities-0.9.6.dist-info/METADATA
gilly_utilities-0.9.6.dist-info/WHEEL
gilly_utilities-0.9.6.dist-info/top_level.txt
gilly_utilities-0.9.6.dist-info/RECORD
