Metadata-Version: 2.1
Name: gilly-utilities
Version: 0.9.6
Summary: A data analysis package built upon Numpy, SciPy and Pandas
Home-page: https://github.com/pacificgilly1992/Gilly_Utilities
Author: James Gilmore
Author-email: jamesgillygilmore@gmail.com
License: UNKNOWN
Platform: UNKNOWN
Classifier: Programming Language :: Python :: 2
Classifier: License :: OSI Approved :: GNU General Public License v3 or later (GPLv3+)
Classifier: Operating System :: OS Independent
Requires-Dist: numpy
Requires-Dist: scipy (!=1.3.0)
Requires-Dist: pandas
Requires-Dist: matplotlib
Requires-Dist: statsmodels
Requires-Dist: scikit-learn
Requires-Dist: scikits.bootstrap
Requires-Dist: patsy
